[
	{	
		"store":"店铺4",
		"trade":"交易成功",
		"imgurl":"../img/54.jpg",
		"title":"斯文印花黑灰色短袖连衣裙111",
		"rmb":"110",
		"shul":"1"
	},
	{	
		"store":"店铺2",
		"trade":"未付款",
		"imgurl":"../img/55.jpg",
		"title":"斯文印花黑灰色短袖连衣裙222",
		"rmb":"120",
		"shul":"3"
	},
	{	
		"store":"店铺6",
		"trade":"正在发货",
		"imgurl":"../img/56.jpg",
		"title":"斯文印花黑灰色短袖连衣裙333",
		"rmb":"119",
		"shul":"2"
	},
	{	
		"store":"店铺9",
		"trade":"待评价",
		"imgurl":"../img/57.jpg",
		"title":"斯文印花黑灰色短袖连衣裙444",
		"rmb":"122",
		"shul":"5"
	},
	{	
		"store":"店铺3",
		"trade":"未发货",
		"imgurl":"../img/58.jpg",
		"title":"斯文印花黑灰色短袖连衣裙555",
		"rmb":"134",
		"shul":"6"
	},
	{	
		"store":"店铺5",
		"trade":"未发货",
		"imgurl":"../img/59.jpg",
		"title":"斯文印花黑灰色短袖连衣裙666",
		"rmb":"169",
		"shul":"3"
	}

]
